idq_geo/__init__.py
idq_geo/__main__.py
idq_geo/convert.py
idq_geo/projection.py
idq_geo/reverse_geocode.py
idq_geo/rg.py
idq_geo/data/EEZ_land_v2_201410.dbf
idq_geo/data/EEZ_land_v2_201410.prj
idq_geo/data/EEZ_land_v2_201410.sbn
idq_geo/data/EEZ_land_v2_201410.sbx
idq_geo/data/EEZ_land_v2_201410.shp
idq_geo/data/EEZ_land_v2_201410.shp.xml
idq_geo/data/EEZ_land_v2_201410.shx
idq_geo/data/world_borders.dbf
idq_geo/data/world_borders.prj
idq_geo/data/world_borders.readme.txt
idq_geo/data/world_borders.shp
idq_geo/data/world_borders.shx
idq_geo-0.2.0.dist-info/DESCRIPTION.rst
idq_geo-0.2.0.dist-info/METADATA
idq_geo-0.2.0.dist-info/RECORD
idq_geo-0.2.0.dist-info/WHEEL
idq_geo-0.2.0.dist-info/metadata.json
idq_geo-0.2.0.dist-info/top_level.txt
