Metadata-Version: 2.0
Name: idq-geo
Version: 0.2.0
Summary: iDigQuality Georeference Validation Module
Home-page: http://github.com/idigbio/idq-geo/
Author: Alex Thompson
Author-email: godfoder@acis.ufl.edu
License: MIT
Platform: UNKNOWN
Classifier: Development Status :: 5 - Production/Stable
Classifier: Intended Audience :: Developers
Classifier: Natural Language :: English
Classifier: License :: OSI Approved :: MIT License
Classifier: Operating System :: OS Independent
Classifier: Programming Language :: Python
Classifier: Programming Language :: Python :: 2
Classifier: Programming Language :: Python :: 2.6
Classifier: Programming Language :: Python :: 2.7
Classifier: Topic :: Software Development :: Libraries :: Python Modules
Requires-Dist: fiona
Requires-Dist: pyproj
Requires-Dist: shapely
